pywikisource/__init__.py
pywikisource-0.0.5.dist-info/LICENSE.txt
pywikisource-0.0.5.dist-info/METADATA
pywikisource-0.0.5.dist-info/WHEEL
pywikisource-0.0.5.dist-info/top_level.txt
pywikisource-0.0.5.dist-info/RECORD
