Metadata-Version: 2.1
Name: pywikisource
Version: 0.0.5
Summary: Wikisource Dedicated Python API library
Home-page: https://github.com/indictechcom/pywikisource
Author: Jay Prakash
Author-email: 0freerunning@gmail.com
Classifier: Programming Language :: Python :: 3
Classifier: License :: OSI Approved :: MIT License
Classifier: Operating System :: OS Independent
License-File: LICENSE.txt
Requires-Dist: requests
Requires-Dist: bs4
Requires-Dist: asyncio
Requires-Dist: aiohttp
